azpersonalizer/__init__.py
azpersonalizer/personalizer_client.py
azpersonalizer/rank_request.py
azpersonalizer/reward_request.py
azpersonalizer-0.0.3.dist-info/DESCRIPTION.rst
azpersonalizer-0.0.3.dist-info/METADATA
azpersonalizer-0.0.3.dist-info/RECORD
azpersonalizer-0.0.3.dist-info/WHEEL
azpersonalizer-0.0.3.dist-info/metadata.json
azpersonalizer-0.0.3.dist-info/top_level.txt
